xtu/__init__.py
xtu/api.py
xtu/const.py
xtu_edu-0.0.1.dist-info/METADATA
xtu_edu-0.0.1.dist-info/WHEEL
xtu_edu-0.0.1.dist-info/top_level.txt
xtu_edu-0.0.1.dist-info/RECORD
