Metadata-Version: 2.4
Name: xtu-edu
Version: 0.0.1
Summary: 湘潭大学教务系统API
Author-email: YangRucheng <admin@yangrucheng.top>
License: MIT
Project-URL: homepage, https://github.com/xtu-org/xtu-edu-captcha
Project-URL: repository, https://github.com/xtu-org/xtu-edu-captcha
Requires-Python: >=3.10
Requires-Dist: httpx>0.28.0
Requires-Dist: xtu-edu-captcha-solver>=0.0.2
Requires-Dist: Beautifulsoup4>=4.13.3
